{
  "width": 11,
  "height": 9,
  "playerStart": {
    "x": 4,
    "y": 6
  },
  "cells": [
    {
      "col": 4,
      "row": 0,
      "layer": 0,
      "properties": [
        "blocked"
      ]
    },
    {
      "col": 5,
      "row": 0,
      "layer": 0,
      "properties": [
        "blocked"
      ]
    },
    {
      "col": 0,
      "row": 1,
      "layer": 0,
      "properties": [
        "blocked"
      ]
    },
    {
      "col": 1,
      "row": 1,
      "layer": 0,
      "properties": [
        "blocked"
      ]
    },
    {
      "col": 2,
      "row": 1,
      "layer": 0,
      "properties": [
        "blocked"
      ]
    },
    {
      "col": 3,
      "row": 1,
      "layer": 0,
      "properties": [
        "blocked"
      ]
    },
    {
      "col": 4,
      "row": 1,
      "layer": 0,
      "properties": [
        "blocked"
      ]
    },
    {
      "col": 5,
      "row": 1,
      "layer": 0,
      "properties": [
        "blocked"
      ],
      "backgroundTexture": {
        "image": "fireplace1",
        "transformOverride": {
          "scaleX": 4,
          "scaleY": 2.9,
          "offsetX": 0,
          "offsetY": -15
        }
      }
    },
    {
      "col": 6,
      "row": 1,
      "layer": 0,
      "properties": [
        "blocked"
      ]
    },
    {
      "col": 7,
      "row": 1,
      "layer": 0,
      "properties": [
        "blocked"
      ]
    },
    {
      "col": 8,
      "row": 1,
      "layer": 0,
      "properties": [
        "blocked"
      ]
    },
    {
      "col": 9,
      "row": 1,
      "layer": 0,
      "properties": [
        "blocked"
      ]
    },
    {
      "col": 10,
      "row": 1,
      "layer": 0,
      "properties": [
        "blocked"
      ]
    },
    {
      "col": 0,
      "row": 2,
      "layer": 0,
      "properties": [
        "blocked"
      ]
    },
    {
      "col": 1,
      "row": 2,
      "layer": 0,
      "properties": [
        "blocked"
      ]
    },
    {
      "col": 2,
      "row": 2,
      "layer": 0,
      "properties": [
        "blocked"
      ],
      "backgroundTexture": {
        "image": "bed1",
        "transformOverride": {
          "scaleX": 3.3,
          "scaleY": 1.5,
          "offsetX": 0,
          "offsetY": -20
        }
      }
    },
    {
      "col": 3,
      "row": 2,
      "layer": 0,
      "properties": [
        "blocked"
      ]
    },
    {
      "col": 5,
      "row": 2,
      "layer": 0,
      "backgroundTexture": {
        "image": "rug2",
        "transformOverride": {
          "scaleX": 1.5,
          "scaleY": 1.5,
          "offsetX": 0,
          "offsetY": 20
        }
      }
    },
    {
      "col": 7,
      "row": 2,
      "layer": 0,
      "properties": [
        "blocked"
      ]
    },
    {
      "col": 8,
      "row": 2,
      "layer": 0,
      "properties": [
        "blocked"
      ],
      "backgroundTexture": {
        "image": "kitchen1",
        "transformOverride": {
          "scaleX": 3.5,
          "scaleY": 2.65,
          "offsetX": 0,
          "offsetY": -50
        }
      }
    },
    {
      "col": 9,
      "row": 2,
      "layer": 0,
      "properties": [
        "blocked"
      ]
    },
    {
      "col": 10,
      "row": 2,
      "layer": 0,
      "properties": [
        "blocked"
      ]
    },
    {
      "col": 0,
      "row": 3,
      "layer": 0,
      "properties": [
        "blocked"
      ]
    },
    {
      "col": 10,
      "row": 3,
      "layer": 0,
      "properties": [
        "blocked"
      ]
    },
    {
      "col": 0,
      "row": 4,
      "layer": 0,
      "properties": [
        "blocked"
      ],
      "backgroundTexture": {
        "image": "sconce_bg",
        "transformOverride": {
          "scaleX": 1,
          "scaleY": 1,
          "offsetX": 20,
          "offsetY": 0
        }
      },
      "animatedTexture": {
        "spritesheet": "sconce_flame",
        "frameWidth": 78,
        "frameHeight": 85,
        "frameCount": 2,
        "frameRate": 8,
        "transformOverride": {
          "scaleX": 0.2,
          "scaleY": 0.2,
          "offsetX": 22,
          "offsetY": -12
        }
      }
    },
    {
      "col": 10,
      "row": 4,
      "layer": 0,
      "properties": [
        "blocked"
      ],
      "backgroundTexture": {
        "image": "sconce_bg",
        "transformOverride": {
          "scaleX": -1,
          "scaleY": 1,
          "offsetX": -20,
          "offsetY": 0
        }
      },
      "animatedTexture": {
        "spritesheet": "sconce_flame",
        "frameWidth": 78,
        "frameHeight": 85,
        "frameCount": 2,
        "frameRate": 8,
        "transformOverride": {
          "scaleX": 0.2,
          "scaleY": 0.2,
          "offsetX": -23,
          "offsetY": -12
        }
      }
    },
    {
      "col": 0,
      "row": 5,
      "layer": 0,
      "properties": [
        "blocked"
      ]
    },
    {
      "col": 3,
      "row": 5,
      "layer": 0,
      "properties": [
        "blocked"
      ]
    },
    {
      "col": 4,
      "row": 5,
      "layer": 0,
      "properties": [
        "blocked"
      ]
    },
    {
      "col": 5,
      "row": 5,
      "layer": 0,
      "properties": [
        "blocked"
      ],
      "backgroundTexture": {
        "image": "table2",
        "transformOverride": {
          "scaleX": 5.7,
          "scaleY": 2.8,
          "offsetX": 0,
          "offsetY": 5
        }
      }
    },
    {
      "col": 6,
      "row": 5,
      "layer": 0,
      "properties": [
        "blocked"
      ]
    },
    {
      "col": 7,
      "row": 5,
      "layer": 0,
      "properties": [
        "blocked"
      ]
    },
    {
      "col": 10,
      "row": 5,
      "layer": 0,
      "properties": [
        "blocked"
      ]
    },
    {
      "col": 0,
      "row": 6,
      "layer": 0,
      "properties": [
        "blocked"
      ]
    },
    {
      "col": 10,
      "row": 6,
      "layer": 0,
      "properties": [
        "blocked"
      ]
    },
    {
      "col": 0,
      "row": 7,
      "layer": 0,
      "properties": [
        "blocked"
      ]
    },
    {
      "col": 10,
      "row": 7,
      "layer": 0,
      "properties": [
        "blocked"
      ]
    },
    {
      "col": 0,
      "row": 8,
      "layer": 0,
      "properties": [
        "blocked"
      ]
    },
    {
      "col": 1,
      "row": 8,
      "layer": 0,
      "properties": [
        "blocked"
      ]
    },
    {
      "col": 2,
      "row": 8,
      "layer": 0,
      "properties": [
        "blocked"
      ]
    },
    {
      "col": 3,
      "row": 8,
      "layer": 0,
      "properties": [
        "blocked"
      ]
    },
    {
      "col": 4,
      "row": 8,
      "layer": 0,
      "properties": [
        "blocked"
      ]
    },
    {
      "col": 5,
      "row": 8,
      "layer": 0,
      "backgroundTexture": {
        "image": "door_closed",
        "transformOverride": {
          "scaleX": 2,
          "scaleY": 1.18,
          "offsetX": 0,
          "offsetY": 0
        }
      }
    },
    {
      "col": 6,
      "row": 8,
      "layer": 0,
      "properties": [
        "blocked"
      ]
    },
    {
      "col": 7,
      "row": 8,
      "layer": 0,
      "properties": [
        "blocked"
      ]
    },
    {
      "col": 8,
      "row": 8,
      "layer": 0,
      "properties": [
        "blocked"
      ]
    },
    {
      "col": 9,
      "row": 8,
      "layer": 0,
      "properties": [
        "blocked"
      ]
    },
    {
      "col": 10,
      "row": 8,
      "layer": 0,
      "properties": [
        "blocked"
      ]
    }
  ],
  "entities": [
    {
      "id": "breakable0",
      "type": "breakable",
      "data": {
        "col": 8,
        "row": 7,
        "texture": "dungeon_vase",
        "health": 1,
        "rarity": "rare"
      },
      "respawnable": true
    },
    {
      "id": "breakable1",
      "type": "breakable",
      "data": {
        "col": 9,
        "row": 7,
        "texture": "dungeon_vase",
        "health": 1,
        "rarity": "rare"
      },
      "respawnable": true
    },
    {
      "id": "breakable2",
      "type": "breakable",
      "data": {
        "col": 2,
        "row": 7,
        "texture": "dungeon_vase",
        "health": 1,
        "rarity": "rare"
      },
      "respawnable": true
    },
    {
      "id": "breakable3",
      "type": "breakable",
      "data": {
        "col": 1,
        "row": 7,
        "texture": "dungeon_vase",
        "health": 1,
        "rarity": "rare"
      },
      "respawnable": true
    },
    {
      "id": "breakable4",
      "type": "breakable",
      "data": {
        "col": 4,
        "row": 2,
        "texture": "dungeon_vase",
        "health": 1,
        "rarity": "rare"
      },
      "respawnable": true
    },
    {
      "id": "breakable6",
      "type": "breakable",
      "data": {
        "col": 6,
        "row": 2,
        "texture": "dungeon_vase",
        "health": 1,
        "rarity": "rare"
      },
      "respawnable": true
    },
    {
      "id": "exit1",
      "type": "exit",
      "data": {
        "targetLevel": "grass_overworld1",
        "targetCol": 35,
        "targetRow": 6,
        "triggerCells": [
          {
            "col": 5,
            "row": 8
          }
        ]
      }
    }
  ],
  "levelTheme": "default",
  "background": {
    "floor_texture": "interior7"
  }
}